CHANGELOG.txt
LICENSE.txt
MANIFEST.in
README.txt
setup.py
tkmlt/__init__.py
tkmlt.egg-info/PKG-INFO
tkmlt.egg-info/SOURCES.txt
tkmlt.egg-info/dependency_links.txt
tkmlt.egg-info/requires.txt
tkmlt.egg-info/top_level.txt