Metadata-Version: 1.1
Name: tkmlt
Version: 0.0.1
Summary: Hand Tracking ML Module
Home-page: UNKNOWN
Author: Sunami Dasgupta
Author-email: sunamidasgupta@gmail.com
License: MIT
Keywords: tkmlt
Platform: UNKNOWN
Classifier: Development Status :: 5 - Production/Stable
Classifier: Intended Audience :: Education
Classifier: Operating System :: Microsoft :: Windows :: Windows 10
Classifier: License :: OSI Approved :: MIT License
Classifier: Programming Language :: Python :: 3
